adiumentum/__init__.py
adiumentum/color.py
adiumentum/comparison.py
adiumentum/converters.py
adiumentum/dependency_sorting.py
adiumentum/display.py
adiumentum/elementary_types.py
adiumentum/enum_utils.py
adiumentum/exceptions.py
adiumentum/file_modification_time.py
adiumentum/frozendict.py
adiumentum/functional.py
adiumentum/import_utils.py
adiumentum/io_utils.py
adiumentum/markers.py
adiumentum/merge.py
adiumentum/numerical.py
adiumentum/paths_manager.py
adiumentum/performance_logging.py
adiumentum/pydantic_extensions.md
adiumentum/pydantic_extensions.py
adiumentum/re_utils.py
adiumentum/string_utils.py
adiumentum/timestamping.py
adiumentum/tuples.py
adiumentum/typing_utils.py
adiumentum-0.6.4.dist-info/WHEEL
adiumentum-0.6.4.dist-info/entry_points.txt
adiumentum-0.6.4.dist-info/METADATA
adiumentum-0.6.4.dist-info/RECORD
