Metadata-Version: 2.3
Name: adiumentum
Version: 0.6.4
Summary: 
Author: Isaac Riley
Author-email: Isaac Riley <yelircaasi@proton.me>
Requires-Dist: pydantic>=2.11
Requires-Dist: multipledispatch>=1
Requires-Dist: loguru>=0.7.3
Requires-Python: >=3.12, <3.15
